riccfe/__init__.py
riccfe-1.0.0.dist-info/METADATA
riccfe-1.0.0.dist-info/WHEEL
riccfe-1.0.0.dist-info/RECORD
