Metadata-Version: 2.4
Name: riccfe
Version: 1.0.0
Summary: Ranked Independent Components (RIC) Explainer for Counterfactual Explanation, leveraging ICA and global optimization.
Project-URL: Homepage, https://github.com/mrajabinasab/RICCFE
Project-URL: Bug Tracker, https://github.com/mrajabinasab/RICCFE/issues
Author-email: Muhammad Rajabinasab <muhammad.rajabinasab@outlook.com>
License: MIT License
Keywords: counterfactuals,explainable-ai,ica,machine-learning,xai
Classifier: Development Status :: 3 - Alpha
Classifier: Intended Audience :: Science/Research
Classifier: License :: OSI Approved :: MIT License
Classifier: Operating System :: OS Independent
Classifier: Programming Language :: Python :: 3
Classifier: Topic :: Scientific/Engineering :: Artificial Intelligence
Requires-Python: >=3.11
Requires-Dist: numpy>=2.3.0
Requires-Dist: pandas>=2.3.0
Requires-Dist: pyswarms>=1.3
Requires-Dist: scikit-learn>=1.7.0
Requires-Dist: scipy>=1.16.0
